async_tcp_chat/LICENSE
async_tcp_chat/__init__.py
async_tcp_chat/tcp_client.py
async_tcp_chat/tcp_gui_client.py
async_tcp_chat/tcp_server.py
async_tcp_chat-0.1.0.dist-info/WHEEL
async_tcp_chat-0.1.0.dist-info/entry_points.txt
async_tcp_chat-0.1.0.dist-info/METADATA
async_tcp_chat-0.1.0.dist-info/RECORD
