Metadata-Version: 2.4
Name: async-tcp-chat
Version: 0.1.0
Summary: Async TCP Chat: peer, server-client, wx GUI mode
Author: Andrea Diamantini
Author-email: Andrea Diamantini <adjam@proton.me>
License-Expression: MIT
Requires-Dist: wxasync>=0.49 ; extra == 'gui'
Requires-Dist: wxpython>=4.2.4 ; extra == 'gui'
Requires-Python: >=3.11
Provides-Extra: gui
